weather_chatbot/__init__.py
weather_chatbot/app.py
weather_chatbot/app_temp.py
weather_chatbot/download_model.py
weather_chatbot/functions.py
weather_chatbot/intents.py
weather_chatbot/push_model.py
weather_chatbot/requirements.txt
weather_chatbot/setup.py
weather_chatbot/style.css
weather_chatbot_phi3-0.1.23.dist-info/METADATA
weather_chatbot_phi3-0.1.23.dist-info/WHEEL
weather_chatbot_phi3-0.1.23.dist-info/entry_points.txt
weather_chatbot_phi3-0.1.23.dist-info/RECORD
