Metadata-Version: 2.1
Name: weather-chatbot-phi3
Version: 0.1.23
Summary: An LLM Chatbot integrated with Open Weather API for Real-Time Weather Information.
License: CC-BY-NC-SA-4.0
Author: Vatsal Patel
Author-email: vatsal1804@gmail.com
Requires-Python: >=3.9,<4.0
Classifier: License :: Other/Proprietary License
Classifier: Programming Language :: Python :: 3
Classifier: Programming Language :: Python :: 3.9
Classifier: Programming Language :: Python :: 3.10
Classifier: Programming Language :: Python :: 3.11
Classifier: Programming Language :: Python :: 3.12
Requires-Dist: datasets (>=2.19.1,<3.0.0)
Requires-Dist: gradio (>=4.32.1,<5.0.0)
Requires-Dist: huggingface-hub (>=0.23.2,<0.24.0)
Requires-Dist: langchain (==0.2.7)
Requires-Dist: langchain_community (==0.2.7)
Requires-Dist: llama-cpp-python (>=0.2.76,<0.3.0)
Requires-Dist: pandas (>=2.0.3,<3.0.0)
Requires-Dist: pytest (>=8.2.1,<9.0.0)
Requires-Dist: requests (>=2.32.3,<3.0.0)
Requires-Dist: tomlkit (==0.12.0)
Requires-Dist: transformers (>=4.41.2,<5.0.0)
